README.md
setup.py
datakund_bot_studio/DataKund.exe
datakund_bot_studio/GetAttributes.py
datakund_bot_studio/GetData.py
datakund_bot_studio/Progress.py
datakund_bot_studio/__init__.py
datakund_bot_studio/datakund_bot_studio.py
datakund_bot_studio/dk_studio.py
datakund_bot_studio/install.py
datakund_bot_studio.egg-info/PKG-INFO
datakund_bot_studio.egg-info/SOURCES.txt
datakund_bot_studio.egg-info/dependency_links.txt
datakund_bot_studio.egg-info/entry_points.txt
datakund_bot_studio.egg-info/requires.txt
datakund_bot_studio.egg-info/top_level.txt